Workbook

Sheet Dataset
A1: INSTRUCCIONES
A2: Este archivo contiene datos ficticios de ventas de Motores Modernos S.A. para el año 2024. Utiliza este dataset en la hoja 'Ejercicios' para completar los ejercicios solicitados. NO modifiques los datos de esta hoja.
A4: ID Venta | B4: Fecha | C4: Región | D4: Vendedor | E4: Producto | F4: Unidades Vendidas | G4: Precio Unit. ($) | H4: Costo Unit. ($) | I4: MES | J4: INGRESO
A5: V-001 | B5: 45600 | C5: Ciudad de Panamá | D5: Laura Torres | E5: Hyundai Tucson | F5: 2 | G5: 28000 | H5: 22500 | I5: =TEXT(B5,"MMM") -> nov | J5: =F5*G5 -> 56000
A6: V-002 | B6: 45375 | C6: Ciudad de Panamá | D6: Sofía Castillo | E6: Toyota Corolla | F6: 5 | G6: 22500 | H6: 18000 | I6: =TEXT(B6,"MMM") -> mar | J6: =F6*G6 -> 112500
A7: V-003 | B7: 45475 | C7: Ciudad de Panamá | D7: Ana Rodríguez | E7: Hyundai Tucson | F7: 2 | G7: 28000 | H7: 22500 | I7: =TEXT(B7,"MMM") -> jul | J7: =F7*G7 -> 56000
A8: V-004 | B8: 45555 | C8: Ciudad de Panamá | D8: Sofía Castillo | E8: Hyundai Tucson | F8: 5 | G8: 28000 | H8: 22500 | I8: =TEXT(B8,"MMM") -> sep | J8: =F8*G8 -> 140000
A9: V-005 | B9: 45481 | C9: Herrera | D9: Sofía Castillo | E9: Kia Sportage | F9: 1 | G9: 25000 | H9: 20000 | I9: =TEXT(B9,"MMM") -> jul | J9: =F9*G9 -> 25000
A10: V-006 | B10: 45374 | C10: Herrera | D10: Laura Torres | E10: Kia Sportage | F10: 2 | G10: 25000 | H10: 20000 | I10: =TEXT(B10,"MMM") -> mar | J10: =F10*G10 -> 50000
A11: V-007 | B11: 45407 | C11: Colón | D11: Ana Rodríguez | E11: Toyota Corolla | F11: 4 | G11: 22500 | H11: 18000 | I11: =TEXT(B11,"MMM") -> abr | J11: =F11*G11 -> 90000
A12: V-008 | B12: 45334 | C12: Colón | D12: Sofía Castillo | E12: Kia Sportage | F12: 1 | G12: 25000 | H12: 20000 | I12: =TEXT(B12,"MMM") -> feb | J12: =F12*G12 -> 25000
A13: V-009 | B13: 45641 | C13: Veraguas | D13: Ana Rodríguez | E13: Mazda CX-5 | F13: 1 | G13: 30000 | H13: 24000 | I13: =TEXT(B13,"MMM") -> dic | J13: =F13*G13 -> 30000
A14: V-010 | B14: 45545 | C14: Veraguas | D14: Laura Torres | E14: Suzuki Swift | F14: 2 | G14: 16000 | H14: 12800 | I14: =TEXT(B14,"MMM") -> sep | J14: =F14*G14 -> 32000
A15: V-011 | B15: 45629 | C15: Ciudad de Panamá | D15: Carlos Méndez | E15: Kia Sportage | F15: 1 | G15: 25000 | H15: 20000 | I15: =TEXT(B15,"MMM") -> dic | J15: =F15*G15 -> 25000
A16: V-012 | B16: 45410 | C16: Ciudad de Panamá | D16: Miguel Ureña | E16: Kia Sportage | F16: 4 | G16: 25000 | H16: 20000 | I16: =TEXT(B16,"MMM") -> abr | J16: =F16*G16 -> 100000
... A64: V-060 | B64: 45306 | C64: Veraguas | D64: Sofía Castillo | E64: Toyota Corolla | F64: 1 | G64: 22500 | H64: 18000 | I64: =TEXT(B64,"MMM") -> ene | J64: =F64*G64 -> 22500

Sheet Ejercicios
A1: PRUEBA TÉCNICA – ANALISTA JR. DE FINANZAS Y BUSINESS INTELLIGENCE
A2: Motores Modernos S.A. | Candidato: Hermogenes Palacio | Fecha: 07/09/2026
A3: Instrucciones: Utiliza los datos del dataset en la hoja 'Dataset' para responder cada ejercicio. Escribe tus fórmulas directamente en las celdas amarillas. No borres el contenido de las celdas grises.
A5: SECCIÓN 1 – Fórmulas y Funciones Básicas
A6: 1.1 | B6: Calcula el TOTAL de unidades vendidas en todo el año 2024. | G6: =SUM(Dataset!F5:F64) -> 165
A7: 1.2 | B7: Calcula el PROMEDIO del precio unitario de todos los productos. | G7: =AVERAGE(Dataset!G5:G64) -> 23983.333
A8: 1.3 | B8: ¿Cuántas ventas se realizaron en la región 'Ciudad de Panamá'? (usa COUNTIF) | G8: =COUNTIF(Dataset!C5:C64,"Ciudad de Panamá") -> 13
A9: 1.4 | B9: ¿Cuál fue el MONTO TOTAL de ventas? (Unidades × Precio Unit.) Usa SUMPRODUCT. | G9: =SUMPRODUCT(Dataset!F5:F64,Dataset!G5:G64) -> 4048500
A10: 1.5 | B10: ¿Cuántas ventas tienen un Precio Unit. mayor a $25,000? (usa COUNTIF) | G10: =COUNTIF(Dataset!G5:G64,">25000") -> 22
A12: SECCIÓN 2 – Análisis con SUMIF / VLOOKUP / Tablas Dinámicas
A13: Parte A – Fórmulas
A14: 2.1 | B14: Calcula el total de ventas ($) generado por el vendedor 'Carlos Méndez'. Usa SUMIF. | G14: =SUMIF(Dataset!D5:D64,"Carlos Méndez",Dataset!G5:G64) -> 269500
A15: 2.2 | B15: ¿Cuántas unidades se vendieron del producto 'Toyota Corolla'? Usa SUMIF. | G15: =SUMIF(Dataset!E5:E64,"Toyota Corolla",Dataset!F5:F64) -> 39
A16: 2.3 | B16: Crea una tabla resumen (debajo) con el total de ventas ($) por región usando SUMIF para cada región. | G16: Ver filas 18-22
A17: Tabla Resumen – Ventas Totales por Región
A18: Región | C18: % del Total
A19: Ciudad de Panamá | B19: =SUMIF(Dataset!C5:C64,A19, Dataset!F5:F64) -> 35 | C19: =B19 / B$24 -> 0.21212121
A20: Chiriquí | B20: =SUMIF(Dataset!C6:C65,A20, Dataset!F6:F65) -> 24 | C20: =B20 / B$24 -> 0.14545455
A21: Colón | B21: =SUMIF(Dataset!C7:C66,A21, Dataset!F7:F66) -> 31 | C21: =B21 / B$24 -> 0.18787879
A22: Herrera | B22: =SUMIF(Dataset!C8:C67,A22, Dataset!F8:F67) -> 41 | C22: =B22 / B$24 -> 0.24848485
A23: Veraguas | B23: =SUMIF(Dataset!C9:C68,A23, Dataset!F9:F68) -> 34 | C23: =B23 / B$24 -> 0.20606061
A24: TOTAL | B24: =SUM(B19:B23) -> 165 | C24: =B24 / B$24 -> 1
A26: Parte B – Tabla Dinámica
A27: 2.4 Crea una Tabla Dinámica en una nueva hoja llamada 'Tabla Dinámica' que muestre: Filas = Producto, Columnas = Región, Valores = Suma de (Unidades × Precio Unit.). Aplica formato de número con separador de miles.
A29: SECCIÓN 3 – Análisis Financiero: Rentabilidad y KPIs
A30: Usa el dataset para calcular los siguientes indicadores. Completa la tabla:
A31: KPI | B31: Fórmula / Descripción | C31: Resultado
A32: Ingreso Total ($) | C32: =SUM(Dataset!J5:J64) -> 4048500
A33: Costo Total ($) | C33: =SUMPRODUCT(Dataset!F5:F64, Dataset!H5:H64) -> 3242800
A34: Utilidad Bruta ($) | C34: =C32-C33 -> 805700
A35: Margen Bruto (%) | B35: =Utilidad Bruta / Ingreso Total → formato % -> #NAME? | C35: =C34 / C32 -> 0.19901198
A36: Ticket Promedio ($) | B36: =Ingreso Total / Número de ventas -> #NAME? | C36: =C32/SUM(Dataset!F5:F64) -> 24536.364
A37: Producto más vendido | B37: =Usa INDEX/MATCH o MAXIF para identificar el producto con más Unidades -> #NAME? | C37: {=INDEX(Dataset!E$5:E$500, MATCH(MAX(SUMIF(Dataset!E$5:E$500, Dataset!E$5:E$500, Dataset!F$5:F$500)), SUMIF(Dataset!E$5:E$500, Dataset!E$5:E$500, Dataset!F$5:F$500), 0))} -> Hyundai Tucson
A38: Mes con mayores ingresos | B38: =Usa SUMIFS + TEXTO(fecha,"MMMM") para agrupar por mes -> #NAME? | C38: {=INDEX(Dataset!I$5:I$500,MATCH(MAX(SUMIF(Dataset!I$5:I$500,Dataset!I$5:I$500,Dataset!J$5:J$500)),SUMIF(Dataset!I$5:I$500,Dataset!I$5:I$500,Dataset!J$5:J$500),0))} -> abr | D38: {=MAX(SUMIF(Dataset!I$5:I$500,Dataset!I$5:I$500,Dataset!J$5:J$500))} -> 593000
A40: SECCIÓN 4 – Visualización: Gráficos en Excel
A41: 4.1 | B41: Crea un gráfico de BARRAS que muestre el Total de Ventas ($) por Región. Agrégalo en esta hoja o en una nueva hoja llamada 'Gráficos'.
A43: 4.2 | B43: Crea un gráfico de LÍNEA que muestre la evolución mensual del Ingreso Total ($) durante 2024.
A45: 4.3 | B45: Crea un gráfico de TORTA (pie) que muestre la participación (%) de cada Producto en el Ingreso Total.

Sheet Tabla dinamica
B5: Suma de INGRESO | C5: Etiquetas de columna
B6: Etiquetas de fila | C6: Chiriquí | D6: Ciudad de Panamá | E6: Colón | F6: Herrera | G6: Veraguas | H6: Total general
B7: Hyundai Tucson | D7: 252000 | E7: 196000 | F7: 308000 | G7: 364000 | H7: 1120000
B8: Kia Sportage | D8: 200000 | E8: 225000 | F8: 250000 | G8: 150000 | H8: 825000
B9: Mazda CX-5 | C9: 360000 | D9: 180000 | F9: 240000 | G9: 30000 | H9: 810000
B10: Suzuki Swift | C10: 112000 | D10: 48000 | E10: 96000 | F10: 64000 | G10: 96000 | H10: 416000
B11: Toyota Corolla | C11: 112500 | D11: 202500 | E11: 202500 | F11: 180000 | G11: 180000 | H11: 877500
B12: Total general | C12: 584500 | D12: 882500 | E12: 719500 | F12: 1042000 | G12: 820000 | H12: 4048500

Sheet GRAFICAS
A3: Etiquetas de fila | B3: Suma de Unidades Vendidas | C3: Suma de INGRESO | O3: Etiquetas de fila | P3: Suma de INGRESO
A4: Chiriquí | B4: 24 | C4: 584500 | O4: Hyundai Tucson | P4: 1120000
A5: Ciudad de Panamá | B5: 35 | C5: 882500 | O5: Kia Sportage | P5: 825000
A6: Colón | B6: 31 | C6: 719500 | O6: Mazda CX-5 | P6: 810000
A7: Herrera | B7: 41 | C7: 1042000 | O7: Suzuki Swift | P7: 416000
A8: Veraguas | B8: 34 | C8: 820000 | O8: Toyota Corolla | P8: 877500
A9: Total general | B9: 165 | C9: 4048500 | O9: Total general | P9: 4048500
A36: Etiquetas de fila | B36: Suma de INGRESO
A37: ene | B37: 300000
A38: feb | B38: 356000
A39: mar | B39: 399500
A40: abr | B40: 593000
A41: may | B41: 323000
A42: jul | B42: 528500
A43: ago | B43: 228500
A44: sep | B44: 477000
A45: oct | B45: 112500
A46: nov | B46: 333500
A47: dic | B47: 397000
A48: Total general | B48: 4048500

Sheet Prueba Power BI
A1: PRUEBA TÉCNICA – POWER BI
A2: prueba de Power BI
A3: Usando el dataset de la hoja 'Dataset' de este archivo (importa el archivo .xlsx directamente a Power BI Desktop), construye un reporte de análisis de ventas con las siguientes páginas y visualizaciones. Entrega el archivo .pbix con el nombre: APELLIDO_Nombre_PowerBI.pbix
A5: PASO 1 – Preparación de Datos (Power Query)
A6: Importa el archivo Excel y selecciona únicamente la hoja 'Dataset'.
A7: Verifica y asigna correctamente los tipos de datos de cada columna (fecha, número, texto).
A8: Crea una columna calculada en Power Query llamada 'Ingreso Venta' = Unidades Vendidas × Precio Unit. ($).
A9: Crea una columna calculada llamada 'Costo Venta' = Unidades Vendidas × Costo Unit. ($).
A10: Crea una columna llamada 'Utilidad' = Ingreso Venta − Costo Venta.
A11: Asegúrate de que la columna 'Fecha' esté correctamente formateada como tipo Fecha.
A13: PASO 2 – Medidas DAX (Crea las siguientes medidas)
A14: Total Ingresos = SUM([Ingreso Venta])
... A43: Punto extra: Agrega una tabla de fechas (Date Table) con DAX y úsala para análisis time-intelligence.
